bgqsp/__init__.py
bgqsp/cusip.py
bg_qsp-0.1.3.dist-info/LICENSE
bg_qsp-0.1.3.dist-info/METADATA
bg_qsp-0.1.3.dist-info/WHEEL
bg_qsp-0.1.3.dist-info/top_level.txt
bg_qsp-0.1.3.dist-info/RECORD
