Metadata-Version: 2.1
Name: bg-qsp
Version: 0.1.3
Summary: UNKNOWN
Home-page: https://github.com/bondgeek/bgqsp
Author: Bart Mosley
Author-email: bartm@bondgeek.com
License: MIT LICENSE
Platform: UNKNOWN
Classifier: Programming Language :: Python :: 3
Classifier: License :: OSI Approved :: MIT License
